lodge.py
lodge-0.1.0.dist-info/METADATA
lodge-0.1.0.dist-info/WHEEL
lodge-0.1.0.dist-info/top_level.txt
lodge-0.1.0.dist-info/RECORD
