Metadata-Version: 2.1
Name: lodge
Version: 0.1.0
Summary: A structured logging package in Python simple to use.
Home-page: https://github.com/NeowayLabs/lodge
Author: Neoway's ML Platform team
License: MIT
Keywords: logging,structured
Platform: UNKNOWN
Classifier: License :: OSI Approved :: MIT License
Classifier: Programming Language :: Python :: 3
Classifier: Programming Language :: Python :: 3 :: Only
Classifier: Programming Language :: Python :: 3.9
Classifier: Intended Audience :: Developers
